magneticod/__init__.py
magneticod/__main__.py
magneticod/bencode.py
magneticod/bittorrent.py
magneticod/constants.py
magneticod/dht.py
magneticod/persistence.py
magneticod-0.6.0.dist-info/DESCRIPTION.rst
magneticod-0.6.0.dist-info/METADATA
magneticod-0.6.0.dist-info/RECORD
magneticod-0.6.0.dist-info/WHEEL
magneticod-0.6.0.dist-info/entry_points.txt
magneticod-0.6.0.dist-info/metadata.json
magneticod-0.6.0.dist-info/top_level.txt
