Metadata-Version: 2.0
Name: magneticod
Version: 0.6.0
Summary: Autonomous BitTorrent DHT crawler and metadata fetcher.
Home-page: http://magnetico.org
Author: Mert Bora ALPER
Author-email: bora@boramalper.org
License: GNU Affero General Public License v3 or later (AGPLv3+)
Platform: UNKNOWN
Classifier: Development Status :: 2 - Pre-Alpha
Classifier: Environment :: No Input/Output (Daemon)
Classifier: Intended Audience :: End Users/Desktop
Classifier: License :: OSI Approved :: GNU Affero General Public License v3 or later (AGPLv3+)
Classifier: Natural Language :: English
Classifier: Operating System :: POSIX :: Linux
Classifier: Programming Language :: Python :: 3 :: Only
Classifier: Programming Language :: Python :: Implementation :: CPython
Requires-Dist: appdirs (>=1.4.3)
Requires-Dist: better-bencode (>=0.2.1)
Requires-Dist: humanfriendly
Requires-Dist: uvloop (>=0.8.0)
